README.md
setup.py
easymerge/__init__.py
easymerge/merger.py
easymerge.egg-info/PKG-INFO
easymerge.egg-info/SOURCES.txt
easymerge.egg-info/dependency_links.txt
easymerge.egg-info/requires.txt
easymerge.egg-info/top_level.txt