Metadata-Version: 2.1
Name: easymerge
Version: 0.4
Summary: A simple Python library for merging dataframes accommodating variations in language, spelling, and typos. 
Home-page: UNKNOWN
Author: Ethan Mai
Author-email: iam.ethanmai@gmail.com
License: UNKNOWN
Platform: UNKNOWN
